xarray_multiscale/__init__.py
xarray_multiscale/chunks.py
xarray_multiscale/multiscale.py
xarray_multiscale/reducers.py
xarray_multiscale/util.py
xarray_multiscale-2.1.0.dist-info/LICENSE
xarray_multiscale-2.1.0.dist-info/METADATA
xarray_multiscale-2.1.0.dist-info/WHEEL
xarray_multiscale-2.1.0.dist-info/RECORD
